opentelemetry/instrumentation/digma/django/__init__.py
opentelemetry/instrumentation/digma/django/digma_middleware.py
opentelemetry/instrumentation/digma/django/version.py
opentelemetry_instrumentation_digma_django-0.7.3.dist-info/METADATA
opentelemetry_instrumentation_digma_django-0.7.3.dist-info/WHEEL
opentelemetry_instrumentation_digma_django-0.7.3.dist-info/top_level.txt
opentelemetry_instrumentation_digma_django-0.7.3.dist-info/RECORD
