Metadata-Version: 2.1
Name: opentelemetry-instrumentation-digma-django
Version: 0.7.3
Summary: Digma instrumentation for Django
Home-page: https://github.com/digma-ai/opentelemetry-instrumentation-digma-django
Author: Roni Dover
Author-email: rdover@digma.ai
License: UNKNOWN
Project-URL: Bug Reports, https://github.com/digma-ai/opentelemetry-instrumentation-digma-django/issues
Project-URL: Source, https://github.com/digma-ai/opentelemetry-instrumentation-digma-django/
Platform: UNKNOWN
Classifier: Programming Language :: Python :: 3
Classifier: Intended Audience :: Developers
Classifier: License :: OSI Approved :: MIT License
Classifier: Natural Language :: English
Classifier: Operating System :: OS Independent
Requires-Python: >=3.6
Requires-Dist: opentelemetry-sdk (~=1.11)
Requires-Dist: opentelemetry.instrumentation.django (==0.30b1)
